{
    "nodes": {
        "entrances": [
            "105:1", "105:2", "105:3", "105:4", "105:5", "105:6", "105:7",
            "106:1", "106:2", "106:3", "106:4", "106:5", "106:6", "106:7"
        ],
        "treasure": ["0xF44", "0xF45", "0xF46", "0xF47", "0xF48"],
        "djinn": [],
        "flags": []
    },

    "edges": {
        "external": [
            ["105:6", "2:23", "Overworld", true, "", []],
            ["105:7", "2:24", "Overworld", true, "", []]
        ],

        "internal": [
            ["105:1", "105:6", true, false, "", []],
            ["105:3", "105:6", true, false, "", []],
            ["105:4", "105:6", true, false, "", []],
            ["105:5", "105:6", true, false, "", []],
            ["105:6", "105:7", true, false, "", []],
            ["105:1", "106:1", true, true, "", []],
            ["105:2", "106:2", true, true, "", []],
            ["105:3", "106:3", true, true, "", []],
            ["105:4", "106:4", true, true, "", []],
            ["105:5", "106:5", true, true, "", []],
            ["105:2", "0xF45", false, false, "", [ ["Whirlwind", "Reveal"] ]],
            ["105:6", "0xF44", false, false, "", [ ["Lash Pebble"] ]],
            ["105:6", "0xF46", false, false, "", []],

            ["106:1", "106:6", true, false, "", []],
            ["106:2", "106:7", true, false, "", []],
            ["106:6", "106:7", true, true, "", []],
            ["106:1", "0xF47", false, false, "", []],
            ["106:4", "0xF48", false, false, "", []]
        ]
    }
}